duckduckgo_translate/__init__.py
duckduckgo_translate/constants.py
duckduckgo_translate/exceptions.py
duckduckgo_translate/models.py
duckduckgo_translate/translator.py
duckduckgo_translate/utils.py
duckduckgo_translate-0.0.1.dist-info/LICENSE
duckduckgo_translate-0.0.1.dist-info/METADATA
duckduckgo_translate-0.0.1.dist-info/WHEEL
duckduckgo_translate-0.0.1.dist-info/top_level.txt
duckduckgo_translate-0.0.1.dist-info/RECORD
